[
    {
        "_comment": "Scenario 1: only pickupFromTime is there and it is of today",
        "_id":"67b4f92b82c7e554ce953848",
        "reference_number":"LTC_M173837",
        "type_of_load":"IMPORT",
        "status":"PENDING",
        "containerNo":"CAAU8709898",
        "caller":"6255ead1943c1311ee468fd9",
        "callerName":"AMODEI LOGISTICS, INC.",
        "shipperName":"PORT",
        "consigneeName":"CONSIGNEE",
        "emptyOriginName":"RETURN_PORT",
        "consigneeAddress":"CONSINGEE_ADDRESS",
        "lastFreeDay":null,
        "pickupFromTime":"DATE_0_6",
        "pickupToTime":"DATE_0_7",
        "deliveryFromTime":null,
        "deliveryToTime":null,
        "returnFromTime":null,
        "returnToTime":null,
        "revenue":0,
        "totalWeight":0,
        "containerSizeName":"40\\'",
        "containerTypeName":"HC",
        "containerOwnerName":"ZIM"
    },
    {
        "_comment": "Scenario 2: only pickupFromTime is there and it is of today + 2 days",
        "_id":"67b4f92b82c7e554ce953849",
        "reference_number":"LTC_M173838",
        "type_of_load":"IMPORT",
        "status":"PENDING",
        "containerNo":"CAAU8709899",
        "caller":"6255ead1943c1311ee468fd9",
        "callerName":"AMODEI LOGISTICS, INC.",
        "shipperName":"PORT",
        "consigneeName":"CONSIGNEE",
        "emptyOriginName":"RETURN_PORT",
        "consigneeAddress":"CONSINGEE_ADDRESS",
        "lastFreeDay":null,
        "pickupFromTime":"DATE_2_15",
        "pickupToTime":"DATE_2_16",
        "deliveryFromTime":null,
        "deliveryToTime":null,
        "returnFromTime":null,
        "returnToTime":null,
        "revenue":0,
        "totalWeight":0,
        "containerSizeName":"40\\'",
        "containerTypeName":"HC",
        "containerOwnerName":"ZIM"
    },
    {
        "_comment": "Scenario 3: only lastFreeDay is there and it is of today - 1 day",
        "_id":"67b4f92b82c7e554ce95384a",
        "reference_number":"LTC_M173839",
        "type_of_load":"IMPORT",
        "status":"PENDING",
        "containerNo":"CAAU8709900",
        "caller":"6255ead1943c1311ee468fd9",
        "callerName":"AMODEI LOGISTICS, INC.",
        "shipperName":"PORT",
        "consigneeName":"CONSIGNEE",
        "emptyOriginName":"RETURN_PORT",
        "consigneeAddress":"CONSINGEE_ADDRESS",
        "lastFreeDay":"DATE_-1_0",
        "pickupFromTime":null,
        "pickupToTime":null,
        "deliveryFromTime":null,
        "deliveryToTime":null,
        "returnFromTime":null,
        "returnToTime":null,
        "revenue":0,
        "totalWeight":0,
        "containerSizeName":"40\\'",
        "containerTypeName":"HC",
        "containerOwnerName":"ZIM"
    },
    {
        "_comment": "Scenario 4: only lastFreeDay is there and it is of today",
        "_id":"67b4f92b82c7e554ce95384b",
        "reference_number":"LTC_M173840",
        "type_of_load":"IMPORT",
        "status":"PENDING",
        "containerNo":"CAAU8709901",
        "caller":"6255ead1943c1311ee468fd9",
        "callerName":"AMODEI LOGISTICS, INC.",
        "shipperName":"PORT",
        "consigneeName":"CONSIGNEE",
        "emptyOriginName":"RETURN_PORT",
        "consigneeAddress":"CONSINGEE_ADDRESS",
        "lastFreeDay":"DATE_0_0",
        "pickupFromTime":null,
        "pickupToTime":null,
        "deliveryFromTime":null,
        "deliveryToTime":null,
        "returnFromTime":null,
        "returnToTime":null,
        "revenue":0,
        "totalWeight":0,
        "containerSizeName":"40\\'",
        "containerTypeName":"HC",
        "containerOwnerName":"ZIM"
    },
    {
        "_comment": "Scenario 5: only lastFreeDay is there and it is of today + 1 day",
        "_id":"67b4f92b82c7e554ce95384c",
        "reference_number":"LTC_M173841",
        "type_of_load":"IMPORT",
        "status":"PENDING",
        "containerNo":"CAAU8709902",
        "caller":"6255ead1943c1311ee468fd9",
        "callerName":"AMODEI LOGISTICS, INC.",
        "shipperName":"PORT",
        "consigneeName":"CONSIGNEE",
        "emptyOriginName":"RETURN_PORT",
        "consigneeAddress":"CONSINGEE_ADDRESS",
        "lastFreeDay":"DATE_1_0",
        "pickupFromTime":null,
        "pickupToTime":null,
        "deliveryFromTime":null,
        "deliveryToTime":null,
        "returnFromTime":null,
        "returnToTime":null,
        "revenue":0,
        "totalWeight":0,
        "containerSizeName":"40\\'",
        "containerTypeName":"HC",
        "containerOwnerName":"ZIM"
    },
    {
        "_comment": "Scenario 6: only lastFreeDay is there and it is of today + 3 days",
        "_id":"67b4f92b82c7e554ce95384d",
        "reference_number":"LTC_M173842",
        "type_of_load":"IMPORT",
        "status":"PENDING",
        "containerNo":"CAAU8709903",
        "caller":"6255ead1943c1311ee468fd9",
        "callerName":"AMODEI LOGISTICS, INC.",
        "shipperName":"PORT",
        "consigneeName":"CONSIGNEE",
        "emptyOriginName":"RETURN_PORT",
        "consigneeAddress":"CONSINGEE_ADDRESS",
        "lastFreeDay":"DATE_3_0",
        "pickupFromTime":null,
        "pickupToTime":null,
        "deliveryFromTime":null,
        "deliveryToTime":null,
        "returnFromTime":null,
        "returnToTime":null,
        "revenue":0,
        "totalWeight":0,
        "containerSizeName":"40\\'",
        "containerTypeName":"HC",
        "containerOwnerName":"ZIM"
    },
    {
        "_comment": "Scenario 7: only deliveryFromTime is there and it is of today + 1 day and delivery is late",
        "_id":"67b4f92b82c7e554ce95384e",
        "reference_number":"LTC_M173843",
        "type_of_load":"IMPORT",
        "status":"PENDING",
        "containerNo":"CAAU8709904",
        "caller":"6255ead1943c1311ee468fd9",
        "callerName":"AMODEI LOGISTICS, INC.",
        "shipperName":"PORT",
        "consigneeName":"CONSIGNEE",
        "emptyOriginName":"RETURN_PORT",
        "consigneeAddress":"CONSINGEE_ADDRESS",
        "lastFreeDay":null,
        "deliveryFromTime":"DATE_1_15",
        "deliveryToTime":"DATE_1_16",
        "pickupFromTime":null,
        "pickupToTime":null,
        "returnFromTime":null,
        "returnToTime":null,
        "revenue":0,
        "totalWeight":0,
        "containerSizeName":"40\\'",
        "containerTypeName":"HC",
        "containerOwnerName":"ZIM"
    },
    {
        "_comment": "Scenario 8: only deliveryFromTime is there and it is of today + 1 day and delivery is early",
        "_id":"67b4f92b82c7e554ce95384f",
        "reference_number":"LTC_M173844",
        "type_of_load":"IMPORT",
        "status":"PENDING",
        "containerNo":"CAAU8709905",
        "caller":"6255ead1943c1311ee468fd9",
        "callerName":"AMODEI LOGISTICS, INC.",
        "shipperName":"PORT",
        "consigneeName":"CONSIGNEE",
        "emptyOriginName":"RETURN_PORT",
        "consigneeAddress":"CONSINGEE_ADDRESS",
        "lastFreeDay":null,
        "deliveryFromTime":"DATE_1_7",
        "deliveryToTime":"DATE_1_8",
        "pickupFromTime":null,
        "pickupToTime":null,
        "returnFromTime":null,
        "returnToTime":null,
        "revenue":0,
        "totalWeight":0,
        "containerSizeName":"40\\'",
        "containerTypeName":"HC",
        "containerOwnerName":"ZIM"
    },
    {
        "_comment": "Scenario 9: only deliveryFromTime is there and it is of today + 2 day and delivery is early",
        "_id":"67b4f92b82c7e554ce953850",
        "reference_number":"LTC_M173845",
        "type_of_load":"IMPORT",
        "status":"PENDING",
        "containerNo":"CAAU8709906",
        "caller":"6255ead1943c1311ee468fd9",
        "callerName":"AMODEI LOGISTICS, INC.",
        "shipperName":"PORT",
        "consigneeName":"CONSIGNEE",
        "emptyOriginName":"RETURN_PORT",
        "consigneeAddress":"CONSINGEE_ADDRESS",
        "lastFreeDay":null,
        "deliveryFromTime":"DATE_2_7",
        "deliveryToTime":"DATE_2_8",
        "pickupFromTime":null,
        "pickupToTime":null,
        "returnFromTime":null,
        "returnToTime":null,
        "revenue":0,
        "totalWeight":0,
        "containerSizeName":"40\\'",
        "containerTypeName":"HC",
        "containerOwnerName":"ZIM"
    },
    {
        "_comment": "Scenario 10: only deliveryFromTime is there and it is of today + 2 day and delivery is early and lfd is today",
        "_id":"67b4f92b82c7e554ce953851",
        "reference_number":"LTC_M173846",
        "type_of_load":"IMPORT",
        "status":"PENDING",
        "containerNo":"CAAU8709907",
        "caller":"6255ead1943c1311ee468fd9",
        "callerName":"AMODEI LOGISTICS, INC.",
        "shipperName":"PORT",
        "consigneeName":"CONSIGNEE",
        "emptyOriginName":"RETURN_PORT",
        "consigneeAddress":"CONSINGEE_ADDRESS",
        "lastFreeDay":"DATE_0_0",
        "deliveryFromTime":"DATE_2_7",
        "deliveryToTime":"DATE_2_8",
        "pickupFromTime":null,
        "pickupToTime":null,
        "returnFromTime":null,
        "returnToTime":null,
        "revenue":0,
        "totalWeight":0,
        "containerSizeName":"40\\'",
        "containerTypeName":"HC",
        "containerOwnerName":"ZIM"
    },
    {
        "_comment": "Scenario 11: only returnFromTime is there and it is of today + 2 day and return is late",
        "_id":"67b4f92b82c7e554ce953852",
        "reference_number":"LTC_M173847",
        "type_of_load":"IMPORT",
        "status":"PENDING",
        "containerNo":"CAAU8709908",
        "caller":"6255ead1943c1311ee468fd9",
        "callerName":"AMODEI LOGISTICS, INC.",
        "shipperName":"PORT",
        "consigneeName":"CONSIGNEE",
        "emptyOriginName":"RETURN_PORT",
        "consigneeAddress":"CONSINGEE_ADDRESS",
        "lastFreeDay":null,
        "deliveryFromTime":null,
        "deliveryToTime":null,
        "pickupFromTime":null,
        "pickupToTime":null,
        "returnFromTime":"DATE_2_15",
        "returnToTime":"DATE_2_16",
        "revenue":0,
        "totalWeight":0,
        "containerSizeName":"40\\'",
        "containerTypeName":"HC",
        "containerOwnerName":"ZIM"
    },
    {
        "_comment": "Scenario 12: only returnFromTime is there and it is of today + 2 day and return is early",
        "_id":"67b4f92b82c7e554ce953853",
        "reference_number":"LTC_M173848",
        "type_of_load":"IMPORT",
        "status":"PENDING",
        "containerNo":"CAAU8709909",
        "caller":"6255ead1943c1311ee468fd9",
        "callerName":"AMODEI LOGISTICS, INC.",
        "shipperName":"PORT",
        "consigneeName":"CONSIGNEE",
        "emptyOriginName":"RETURN_PORT",
        "consigneeAddress":"CONSINGEE_ADDRESS",
        "lastFreeDay":null,
        "deliveryFromTime":null,
        "deliveryToTime":null,
        "pickupFromTime":null,
        "pickupToTime":null,
        "returnFromTime":"DATE_2_7",
        "returnToTime":"DATE_2_8",
        "revenue":0,
        "totalWeight":0,
        "containerSizeName":"40\\'",
        "containerTypeName":"HC",
        "containerOwnerName":"ZIM"
    },
    {
        "_comment": "Scenario 13: only pickupFromTime and deliveryFromTime is there, pickup is today - 1 day and delivery is today",
        "_id":"67b4f92b82c7e554ce953854",
        "reference_number":"LTC_M173849",
        "type_of_load":"IMPORT",
        "status":"PENDING",
        "containerNo":"CAAU8709910",
        "caller":"6255ead1943c1311ee468fd9",
        "callerName":"AMODEI LOGISTICS, INC.",
        "shipperName":"PORT",
        "consigneeName":"CONSIGNEE",
        "emptyOriginName":"RETURN_PORT",
        "consigneeAddress":"CONSINGEE_ADDRESS",
        "lastFreeDay":null,
        "pickupFromTime":"DATE_-1_10",
        "pickupToTime":"DATE_-1_11",
        "deliveryFromTime":"DATE_0_10",
        "deliveryToTime":"DATE_0_11",
        "returnFromTime":null,
        "returnToTime":null,
        "revenue":0,
        "totalWeight":0,
        "containerSizeName":"40\\'",
        "containerTypeName":"HC",
        "containerOwnerName":"ZIM"
    },
    {
        "_comment": "Scenario 14: only pickupFromTime and deliveryFromTime is there, pickup is today and delivery is today + 3 day",
        "_id":"67b4f92b82c7e554ce953855",
        "reference_number":"LTC_M173850",
        "type_of_load":"IMPORT",
        "status":"PENDING",
        "containerNo":"CAAU8709911",
        "caller":"6255ead1943c1311ee468fd9",
        "callerName":"AMODEI LOGISTICS, INC.",
        "shipperName":"PORT",
        "consigneeName":"CONSIGNEE",
        "emptyOriginName":"RETURN_PORT",
        "consigneeAddress":"CONSINGEE_ADDRESS",
        "lastFreeDay":null,
        "pickupFromTime":"DATE_0_10",
        "pickupToTime":"DATE_0_11",
        "deliveryFromTime":"DATE_3_10",
        "deliveryToTime":"DATE_3_11",
        "returnFromTime":null,
        "returnToTime":null,
        "revenue":0,
        "totalWeight":0,
        "containerSizeName":"40\\'",
        "containerTypeName":"HC",
        "containerOwnerName":"ZIM"
    },
    {
        "_comment": "Scenario 15: only deliveryFromTime and returnFromTime is there, delivery is today and return is today",
        "_id":"67b4f92b82c7e554ce953856",
        "reference_number":"LTC_M173851",
        "type_of_load":"IMPORT",
        "status":"PENDING",
        "containerNo":"CAAU8709912",
        "caller":"6255ead1943c1311ee468fd9",
        "callerName":"AMODEI LOGISTICS, INC.",
        "shipperName":"PORT",
        "consigneeName":"CONSIGNEE",
        "emptyOriginName":"RETURN_PORT",
        "consigneeAddress":"CONSINGEE_ADDRESS",
        "lastFreeDay":null,
        "deliveryFromTime":"DATE_0_10",
        "deliveryToTime":"DATE_0_11",
        "pickupFromTime":null,
        "pickupToTime":null,
        "returnFromTime":"DATE_0_10",
        "returnToTime":"DATE_0_11",
        "revenue":0,
        "totalWeight":0,
        "containerSizeName":"40\\'",
        "containerTypeName":"HC",
        "containerOwnerName":"ZIM"
    },
    {
        "_comment": "Scenario 16: only deliveryFromTime and returnFromTime is there, delivery is today + 1 day and return is today + 2 day",
        "_id":"67b4f92b82c7e554ce953857",
        "reference_number":"LTC_M173852",
        "type_of_load":"IMPORT",
        "status":"PENDING",
        "containerNo":"CAAU8709913",
        "caller":"6255ead1943c1311ee468fd9",
        "callerName":"AMODEI LOGISTICS, INC.",
        "shipperName":"PORT",
        "consigneeName":"CONSIGNEE",
        "emptyOriginName":"RETURN_PORT",
        "consigneeAddress":"CONSINGEE_ADDRESS",
        "lastFreeDay":null,
        "deliveryFromTime":"DATE_1_10",
        "deliveryToTime":"DATE_1_11",
        "pickupFromTime":null,
        "pickupToTime":null,
        "returnFromTime":"DATE_2_10",
        "returnToTime":"DATE_2_11",
        "revenue":0,
        "totalWeight":0,
        "containerSizeName":"40\\'",
        "containerTypeName":"HC",
        "containerOwnerName":"ZIM"
    },
    {
        "_comment": "Scenario 17: pickupFromTime, deliveryFromTime and returnFromTime is there, pickup is today, delivery is today + 1 day and return is today + 2 day",
        "_id":"67b4f92b82c7e554ce953858",
        "reference_number":"LTC_M173853",
        "type_of_load":"IMPORT",
        "status":"PENDING",
        "containerNo":"CAAU8709914",
        "caller":"6255ead1943c1311ee468fd9",
        "callerName":"AMODEI LOGISTICS, INC.",
        "shipperName":"PORT",
        "consigneeName":"CONSIGNEE",
        "emptyOriginName":"RETURN_PORT",
        "consigneeAddress":"CONSINGEE_ADDRESS",
        "lastFreeDay":null,
        "pickupFromTime":"DATE_0_10",
        "pickupToTime":"DATE_0_11",
        "deliveryFromTime":"DATE_1_10",
        "deliveryToTime":"DATE_1_11",
        "returnFromTime":"DATE_2_10",
        "returnToTime":"DATE_2_11",
        "revenue":0,
        "totalWeight":0,
        "containerSizeName":"40\\'",
        "containerTypeName":"HC",
        "containerOwnerName":"ZIM"
    }
]